rustytables-0.1.1.dist-info/METADATA
rustytables-0.1.1.dist-info/WHEEL
rustytables-0.1.1.dist-info/license_files/LICENSE
rustytables/__init__.py
rustytables/rustytables.cpython-311-darwin.so
rustytables-0.1.1.dist-info/RECORD
