Metadata-Version: 2.3
Name: rustytables
Version: 0.1.1
License-File: LICENSE
Summary: A Rust library for pretty tables in Python
Author-email: Jahidul Hasan <jhhemalusa@gmail.com>
License: MIT
